django_cloud_tasks/__init__.py
django_cloud_tasks/apps.py
django_cloud_tasks/context.py
django_cloud_tasks/exceptions.py
django_cloud_tasks/field.py
django_cloud_tasks/models.py
django_cloud_tasks/serializers.py
django_cloud_tasks/signals.py
django_cloud_tasks/urls.py
django_cloud_tasks/views.py
django_cloud_tasks/management/__init__.py
django_cloud_tasks/management/commands/__init__.py
django_cloud_tasks/management/commands/initialize_subscribers.py
django_cloud_tasks/management/commands/initialize_tasks.py
django_cloud_tasks/management/commands/schedule_tasks.py
django_cloud_tasks/middleware/__init__.py
django_cloud_tasks/middleware/headers_context_middlware.py
django_cloud_tasks/middleware/pubsub_headers_middleware.py
django_cloud_tasks/migrations/0001_initial.py
django_cloud_tasks/migrations/0002_alter_routine_status_alter_routine_task_name.py
django_cloud_tasks/migrations/0003_alter_routine_max_retries_and_more.py
django_cloud_tasks/migrations/__init__.py
django_cloud_tasks/tasks/__init__.py
django_cloud_tasks/tasks/helpers.py
django_cloud_tasks/tasks/periodic_task.py
django_cloud_tasks/tasks/publisher_task.py
django_cloud_tasks/tasks/routine_task.py
django_cloud_tasks/tasks/subscriber_task.py
django_cloud_tasks/tasks/task.py
django_cloud_tasks/tests/__init__.py
django_cloud_tasks/tests/factories.py
django_cloud_tasks/tests/tests_base.py
django_google_cloud_tasks-2.21.0.dist-info/METADATA
django_google_cloud_tasks-2.21.0.dist-info/WHEEL
django_google_cloud_tasks-2.21.0.dist-info/licenses/LICENSE.md
django_google_cloud_tasks-2.21.0.dist-info/RECORD
