Metadata-Version: 2.4
Name: django-google-cloud-tasks
Version: 2.21.0
Summary: Async Tasks with HTTP endpoints
Author-email: Joao Daher <joao@daher.dev>
Maintainer: Lucas Gomide, Rodrigo Almeida, Diego Freire, Guilherme Araujo
License-File: LICENSE.md
Requires-Python: >=3.11
Requires-Dist: django>=4
Requires-Dist: drf-kit>=1.45.0
Requires-Dist: gcp-pilot[pubsub,tasks]>=1.32.0
